<?xml version="1.0"?>

<System>

<Devices>
    <dev name="Dummy" lib="libdummyDev.dylib"/>
</Devices>

<Objects>

<obj name="plat" type="Platform">

    <attributes>
        <attr name="POWER" op="SUM">
            <src type="child" name="cab0" />
        </attr>
    </attributes>

    <children>
        <child name="cab0" />
    </children>

</obj>

<obj name="plat.cab0" type="Cabinet" >

    <attributes>
        <attr name="POWER" op="SUM" >
            <src type="child" name="board0" />
        </attr>
    </attributes>

    <children>
        <child name="board0" />
    </children>

</obj >

<obj name="plat.cab0.board0" type="Board" >

    <attributes>
        <attr name="POWER" op="SUM" >
            <src type="child" name="node0" />
        </attr>
    </attributes>

    <children>
        <child name="node0" />
    </children>

</obj >

<obj name="plat.cab0.board0.node0" type="Node" >

    <attributes>
        <attr name="POWER" op="SUM" >
            <src type="child" name="socket0" />
        </attr>
    </attributes>

    <children>
        <child name="socket0" />
    </children>

</obj >

<obj name="plat.cab0.board0.node0.socket0" type="Socket" >

    <attributes>
        <attr name="POWER" op="SUM" >
            <src type="child" name="core0" />
            <src type="child" name="core1" />
        </attr>
    </attributes>

    <children>
        <child name="core0"/>
        <child name="core1"/>
    </children>

</obj >

<obj name="plat.cab0.board0.node0.socket0.core0" type="Core" >

    <attributes>
        <attr name="VOLTAGE" op="">
            <src type="plugin" name="Dummy" initString="port=1" />
        </attr>
        <attr name="CURRENT" op="" >
            <src type="plugin" name="Dummy" initString="port=2" />
        </attr>
        <attr name="POWER" op="SUM" >
            <src type="plugin" name="Dummy" initString="port=3" />
        </attr>
    </attributes>

</obj >

<obj name="plat.cab0.board0.node0.socket0.core1" type="Core" >

    <attributes>
        <attr name="VOLTAGE" op="" >
            <src type="plugin" name="Dummy" initString="port=4" />
        </attr>
        <attr name="CURRENT" op="" >
            <src type="plugin" name="Dummy" initString="port=5" />
        </attr>
        <attr name="POWER" op="SUM" >
            <src type="plugin" name="Dummy" initString="port=6" />
        </attr>
    </attributes>

</obj >

</Objects>
</System>
